eldar_wordle/__init__.py
eldar_wordle/game.py
eldar_wordle/words.py
eldar_wordle-1.0.0.dist-info/METADATA
eldar_wordle-1.0.0.dist-info/WHEEL
eldar_wordle-1.0.0.dist-info/entry_points.txt
eldar_wordle-1.0.0.dist-info/top_level.txt
eldar_wordle-1.0.0.dist-info/RECORD
