Metadata-Version: 2.4
Name: eldar-wordle
Version: 1.0.0
Summary: CLI Wordle game (5-letter guessing game)
Author: Eldar
Requires-Python: >=3.8
